dhlmex/__init__.py
dhlmex/client.py
dhlmex/exceptions.py
dhlmex/py.typed
dhlmex/version.py
dhlmex/resources/__init__.py
dhlmex/resources/base.py
dhlmex/resources/destination.py
dhlmex/resources/guides.py
dhlmex/resources/order_details.py
dhlmex/resources/origin.py
dhlmex/resources/post_codes.py
dhlmex-0.0.5.dist-info/LICENSE
dhlmex-0.0.5.dist-info/METADATA
dhlmex-0.0.5.dist-info/WHEEL
dhlmex-0.0.5.dist-info/top_level.txt
dhlmex-0.0.5.dist-info/RECORD
