Metadata-Version: 2.1
Name: dhlmex
Version: 0.0.5
Summary: Client library for DHL in Mexico
Home-page: https://github.com/cuenca-mx/dhlmex-python
Author: Cuenca
Author-email: dev@cuenca.com
License: UNKNOWN
Platform: UNKNOWN
Classifier: Programming Language :: Python :: 3
Classifier: Programming Language :: Python :: 3.6
Classifier: Programming Language :: Python :: 3.7
Classifier: License :: OSI Approved :: MIT License
Classifier: Operating System :: OS Independent
Requires-Python: >=3.6
Requires-Dist: requests (<3.0.0,>=2.22.0)
Requires-Dist: beautifulsoup4 (>=4.8.1)
Requires-Dist: Unidecode (==1.1.1)
Requires-Dist: dataclasses (>=0.6) ; python_version < "3.7"
Provides-Extra: test
Requires-Dist: pytest ; extra == 'test'
Requires-Dist: pytest-vcr ; extra == 'test'
Requires-Dist: pycodestyle ; extra == 'test'
Requires-Dist: pytest-cov ; extra == 'test'
Requires-Dist: black ; extra == 'test'
Requires-Dist: isort[pipfile] ; extra == 'test'
Requires-Dist: flake8 ; extra == 'test'
Requires-Dist: mypy ; extra == 'test'
